CHANGES.rst
COPYING.txt
pyramid_heroku/__init__.py
pyramid_heroku/client_addr.py
pyramid_heroku/heroku.py
pyramid_heroku/herokuapp_access.py
pyramid_heroku/host.py
pyramid_heroku/maintenance.py
pyramid_heroku/migrate.py
pyramid_heroku/py.typed
pyramid_heroku/tests/__init__.py
pyramid_heroku/tests/test_client_addr.py
pyramid_heroku/tests/test_heroku.py
pyramid_heroku/tests/test_herokuapp_access.py
pyramid_heroku/tests/test_host.py
pyramid_heroku/tests/test_maintenance.py
pyramid_heroku/tests/test_migrate.py
pyramid_heroku/tests/test_utils.py
pyramid_heroku-0.11.dist-info/COPYING.txt
pyramid_heroku-0.11.dist-info/METADATA
pyramid_heroku-0.11.dist-info/WHEEL
pyramid_heroku-0.11.dist-info/RECORD
