Metadata-Version: 2.1
Name: pyramid_heroku
Version: 0.11
Summary: A bunch of helpers for successfully running Pyramid on Heroku.
Home-page: https://github.com/teamniteo/pyramid_heroku
License: BSD-3-Clause
Keywords: pyramid,heroku,pylons,web
Author: Niteo
Author-email: info@niteo.co
Requires-Python: >=3.6
Classifier: Development Status :: 4 - Beta
Classifier: Framework :: Pylons
Classifier: Intended Audience :: Developers
Classifier: License :: OSI Approved :: BSD License
Classifier: Operating System :: OS Independent
Classifier: Programming Language :: Python
Classifier: Programming Language :: Python :: 3
Classifier: Programming Language :: Python :: 3.6
Classifier: Programming Language :: Python :: 3.7
Classifier: Programming Language :: Python :: 3.8
Classifier: Programming Language :: Python :: 3.9
Classifier: Programming Language :: Python :: 3.10
Classifier: Programming Language :: Python :: 3.11
Classifier: Programming Language :: Python :: 3.12
Classifier: Topic :: Internet :: WWW/HTTP
Classifier: Topic :: Internet :: WWW/HTTP :: WSGI
Classifier: Topic :: Software Development :: Libraries :: Python Modules
Requires-Dist: expandvars
Requires-Dist: pyramid (>=1.7)
Requires-Dist: requests
